throttle/__init__.py
throttle/configs.py
throttle/controller.py
throttle/lock.py
throttle/node.py
throttle/task.py
throttle/utils.py
throttle/web.py
throttle/data/.gitkeep
fn_throttle-0.0.1.dist-info/LICENSE
fn_throttle-0.0.1.dist-info/METADATA
fn_throttle-0.0.1.dist-info/WHEEL
fn_throttle-0.0.1.dist-info/top_level.txt
fn_throttle-0.0.1.dist-info/RECORD
