Metadata-Version: 2.1
Name: fn-throttle
Version: 0.0.1
Summary: Standalone python function call controller
Home-page: https://github.com/ZhenningLang/throttle
Author: ZhenningLang
Author-email: zhenninglang@163.com
License: UNKNOWN
Platform: UNKNOWN
Classifier: Programming Language :: Python :: 3
Classifier: License :: OSI Approved :: MIT License
Classifier: Operating System :: OS Independent
Requires-Python: >=3.2
